[
  {
    "ts": "2026-07-13T16:07:13.292Z",
    "when": "Jul 13 · 4:07 PM",
    "title": "So Far Away",
    "artist": "Alison's Halo",
    "album": "Skywide"
  },
  {
    "ts": "2026-07-13T16:02:34.023Z",
    "when": "Jul 13 · 4:02 PM",
    "title": "Cherry",
    "artist": "Chromatics",
    "album": "Don't Come Back From The Moon (Original Motion Picture Soundtrack)"
  },
  {
    "ts": "2026-07-13T15:57:41.935Z",
    "when": "Jul 13 · 3:57 PM",
    "title": "Into the Night",
    "artist": "Julee Cruise",
    "album": "Soundtrack From Twin Peaks"
  },
  {
    "ts": "2026-07-13T15:52:57.161Z",
    "when": "Jul 13 · 3:52 PM",
    "title": "Will I See You Again?",
    "artist": "Thee Sacred Souls",
    "album": "Will I See You Again?"
  },
  {
    "ts": "2026-07-13T15:48:56.090Z",
    "when": "Jul 13 · 3:48 PM",
    "title": "Blue Moon - 1999 Remastered",
    "artist": "Frank Sinatra",
    "album": "Sinatra's Swingin' Session!!! And More (Remastered / Expanded Edition)"
  },
  {
    "ts": "2026-07-13T15:46:04.216Z",
    "when": "Jul 13 · 3:46 PM",
    "title": "Lazy Nina",
    "artist": "Greg Phillinganes",
    "album": "Pulse (Expanded Edition)"
  },
  {
    "ts": "2026-07-13T15:40:37.164Z",
    "when": "Jul 13 · 3:40 PM",
    "title": "Sometimes",
    "artist": "Dreamgirl",
    "album": "Sometimes"
  },
  {
    "ts": "2026-07-13T15:37:48.449Z",
    "when": "Jul 13 · 3:37 PM",
    "title": "Setting Sun",
    "artist": "You'll Never Get to Heaven",
    "album": "Wave Your Moonlight Hat For The Snowfall Train"
  },
  {
    "ts": "2026-07-13T15:34:49.175Z",
    "when": "Jul 13 · 3:34 PM",
    "title": "Sarah",
    "artist": "Alex G",
    "album": "Trick"
  },
  {
    "ts": "2026-07-13T15:31:22.612Z",
    "when": "Jul 13 · 3:31 PM",
    "title": "Home",
    "artist": "Vacations",
    "album": "Vibes"
  },
  {
    "ts": "2026-07-13T15:28:56.370Z",
    "when": "Jul 13 · 3:28 PM",
    "title": "Away",
    "artist": "Vacations",
    "album": "Vibes"
  },
  {
    "ts": "2026-07-13T15:26:13.586Z",
    "when": "Jul 13 · 3:26 PM",
    "title": "Honey",
    "artist": "Vacations",
    "album": "Changes"
  },
  {
    "ts": "2026-07-13T15:23:53.548Z",
    "when": "Jul 13 · 3:23 PM",
    "title": "Relax",
    "artist": "Vacations",
    "album": "Vibes"
  },
  {
    "ts": "2026-07-13T14:58:07.676Z",
    "when": "Jul 13 · 2:58 PM",
    "title": "Already Gone",
    "artist": "RICEWINE",
    "album": "Already Gone"
  },
  {
    "ts": "2026-07-13T14:55:08.252Z",
    "when": "Jul 13 · 2:55 PM",
    "title": "Over the Moon",
    "artist": "The Marías",
    "album": "Superclean, Vol. II"
  },
  {
    "ts": "2026-07-13T14:52:04.919Z",
    "when": "Jul 13 · 2:52 PM",
    "title": "All I Need",
    "artist": "Radiohead",
    "album": "In Rainbows"
  },
  {
    "ts": "2026-07-13T14:48:15.727Z",
    "when": "Jul 13 · 2:48 PM",
    "title": "Metamodernity",
    "artist": "Vansire",
    "album": "Metamodernity"
  },
  {
    "ts": "2026-07-13T14:45:32.612Z",
    "when": "Jul 13 · 2:45 PM",
    "title": "All Night Long",
    "artist": "Pachyman, Winter",
    "album": "El Sonido Nuevo de"
  },
  {
    "ts": "2026-07-13T14:41:12.015Z",
    "when": "Jul 13 · 2:41 PM",
    "title": "Voice of no Return - Guitar",
    "artist": "岡部啓一",
    "album": "NieR:Automata Original Soundtrack"
  },
  {
    "ts": "2026-07-13T14:37:19.727Z",
    "when": "Jul 13 · 2:37 PM",
    "title": "Different This Time",
    "artist": "Cornelia Murr",
    "album": "Lake Tear of the Clouds"
  },
  {
    "ts": "2026-07-13T13:50:46.344Z",
    "when": "Jul 13 · 1:50 PM",
    "title": "Hai Bby",
    "artist": "The Bilinda Butchers",
    "album": "Goodbyes"
  },
  {
    "ts": "2026-07-13T13:47:28.176Z",
    "when": "Jul 13 · 1:47 PM",
    "title": "Melanie",
    "artist": "TV Girl",
    "album": "Lonely Women"
  },
  {
    "ts": "2026-07-13T13:42:49.501Z",
    "when": "Jul 13 · 1:42 PM",
    "title": "Strange Things Will Happen",
    "artist": "The Radio Dept.",
    "album": "Lesser Matters"
  },
  {
    "ts": "2026-07-13T13:38:21.724Z",
    "when": "Jul 13 · 1:38 PM",
    "title": "Preoccupied",
    "artist": "Mac DeMarco",
    "album": "Here Comes The Cowboy"
  },
  {
    "ts": "2026-07-13T13:32:43.074Z",
    "when": "Jul 13 · 1:32 PM",
    "title": "All U Wanna Do Is Dance",
    "artist": "Dreamgirl",
    "album": "All U Wanna Do Is Dance"
  },
  {
    "ts": "2026-07-13T13:29:33.827Z",
    "when": "Jul 13 · 1:29 PM",
    "title": "Fortress of Lies",
    "artist": "岡部啓一",
    "album": "NieR:Automata Original Soundtrack"
  },
  {
    "ts": "2026-07-13T13:26:26.890Z",
    "when": "Jul 13 · 1:26 PM",
    "title": "Tesselation",
    "artist": "Mild High Club",
    "album": "Skiptracing"
  },
  {
    "ts": "2026-07-13T13:14:43.538Z",
    "when": "Jul 13 · 1:14 PM",
    "title": "From the Subway Train",
    "artist": "Vansire",
    "album": "Angel Youth"
  },
  {
    "ts": "2026-07-13T13:13:45.733Z",
    "when": "Jul 13 · 1:13 PM",
    "title": "honeydew blue - Remastered",
    "artist": "800 cherries",
    "album": "romantico (2022 Remaster)"
  },
  {
    "ts": "2026-07-13T05:19:21.244Z",
    "when": "Jul 13 · 5:19 AM",
    "title": "Caught In Time, So Far Away",
    "artist": "You'll Never Get to Heaven",
    "album": "Adorn"
  },
  {
    "ts": "2026-07-13T05:15:32.135Z",
    "when": "Jul 13 · 5:15 AM",
    "title": "Birch Tree",
    "artist": "Strawberry Guy",
    "album": "Taking My Time to Be"
  },
  {
    "ts": "2026-07-13T05:10:51.156Z",
    "when": "Jul 13 · 5:10 AM",
    "title": "Lost",
    "artist": "Autumn's Grey Solace",
    "album": "Within The Depths Of A Darkened Forest"
  },
  {
    "ts": "2026-07-13T05:07:16.353Z",
    "when": "Jul 13 · 5:07 AM",
    "title": "Dreampopper's Tribute",
    "artist": "Rumskib",
    "album": "Rumskib (Expanded Version)"
  },
  {
    "ts": "2026-07-13T05:00:18.421Z",
    "when": "Jul 13 · 5:00 AM",
    "title": "The Blonde",
    "artist": "TV Girl",
    "album": "French Exit"
  },
  {
    "ts": "2026-07-13T04:56:30.185Z",
    "when": "Jul 13 · 4:56 AM",
    "title": "Home",
    "artist": "Vacations",
    "album": "Vibes"
  },
  {
    "ts": "2026-07-13T04:54:04.082Z",
    "when": "Jul 13 · 4:54 AM",
    "title": "Where Are You",
    "artist": "54 Ultra",
    "album": "Where Are You"
  },
  {
    "ts": "2026-07-13T04:51:40.870Z",
    "when": "Jul 13 · 4:51 AM",
    "title": "Talk to Strangers",
    "artist": "TV Girl",
    "album": "French Exit"
  },
  {
    "ts": "2026-07-13T04:48:42.718Z",
    "when": "Jul 13 · 4:48 AM",
    "title": "You Say I'm in Love",
    "artist": "Banes World",
    "album": "You Say I'm in Love"
  },
  {
    "ts": "2026-07-13T02:31:38.864Z",
    "when": "Jul 13 · 2:31 AM",
    "title": "Cranekiss",
    "artist": "Tamaryn",
    "album": "Cranekiss"
  },
  {
    "ts": "2026-07-13T02:21:58.792Z",
    "when": "Jul 13 · 2:21 AM",
    "title": "Cranekiss",
    "artist": "Tamaryn",
    "album": "Cranekiss"
  },
  {
    "ts": "2026-07-13T02:18:07.956Z",
    "when": "Jul 13 · 2:18 AM",
    "title": "Talk 2 Me",
    "artist": "54 Ultra",
    "album": "Talk 2 Me"
  },
  {
    "ts": "2026-07-13T02:15:00.881Z",
    "when": "Jul 13 · 2:15 AM",
    "title": "Lies in the Eyes of Love",
    "artist": "Part Time",
    "album": "Lies in the Eyes of Love"
  },
  {
    "ts": "2026-07-13T02:11:44.079Z",
    "when": "Jul 13 · 2:11 AM",
    "title": "Telephones",
    "artist": "Vacations",
    "album": "Changes"
  },
  {
    "ts": "2026-07-13T02:08:11.797Z",
    "when": "Jul 13 · 2:08 AM",
    "title": "Moving Out",
    "artist": "Vacations",
    "album": "Changes"
  },
  {
    "ts": "2026-07-13T01:59:01.599Z",
    "when": "Jul 13 · 1:59 AM",
    "title": "Moving Out",
    "artist": "Vacations",
    "album": "Changes"
  },
  {
    "ts": "2026-07-12T20:56:39.460Z",
    "when": "Jul 12 · 8:56 PM",
    "title": "Moving Out",
    "artist": "Vacations",
    "album": "Changes"
  },
  {
    "ts": "2026-07-12T17:23:52.592Z",
    "when": "Jul 12 · 5:23 PM",
    "title": "Look For The Silver Lining",
    "artist": "Chet Baker",
    "album": "Chet Baker Sings"
  },
  {
    "ts": "2026-07-12T17:21:12.740Z",
    "when": "Jul 12 · 5:21 PM",
    "title": "Sometimes",
    "artist": "Dreamgirl",
    "album": "Sometimes"
  },
  {
    "ts": "2026-07-12T17:18:49.254Z",
    "when": "Jul 12 · 5:18 PM",
    "title": "Ghosts (From The Runarounds Original Series)",
    "artist": "The Runarounds",
    "album": "The Runarounds (Prime Video Original Series Soundtrack)"
  },
  {
    "ts": "2026-07-12T17:16:05.314Z",
    "when": "Jul 12 · 5:16 PM",
    "title": "Lazy Nina",
    "artist": "Greg Phillinganes",
    "album": "Pulse (Expanded Edition)"
  },
  {
    "ts": "2026-07-12T17:10:23.895Z",
    "when": "Jul 12 · 5:10 PM",
    "title": "Her House",
    "artist": "The Moon Seven Times",
    "album": "The Moon Seven Times"
  },
  {
    "ts": "2026-07-11T19:01:08.586Z",
    "when": "Jul 11 · 7:01 PM",
    "title": "ALUCARDA",
    "artist": "INOHA",
    "album": "ALUCARDA"
  },
  {
    "ts": "2026-07-11T18:57:32.460Z",
    "when": "Jul 11 · 6:57 PM",
    "title": "Halo",
    "artist": "54 Ultra",
    "album": "First Works"
  },
  {
    "ts": "2026-07-11T18:54:38.713Z",
    "when": "Jul 11 · 6:54 PM",
    "title": "Blind Dumb Deaf",
    "artist": "Cocteau Twins",
    "album": "Garlands"
  },
  {
    "ts": "2026-07-11T18:50:51.456Z",
    "when": "Jul 11 · 6:50 PM",
    "title": "Go Getter",
    "artist": "Moxie",
    "album": "The Fall LP"
  },
  {
    "ts": "2026-07-11T18:47:22.963Z",
    "when": "Jul 11 · 6:47 PM",
    "title": "lucy~",
    "artist": "Corbon Amodio",
    "album": "lucy~"
  },
  {
    "ts": "2026-07-11T18:45:22.620Z",
    "when": "Jul 11 · 6:45 PM",
    "title": "The Way You Look Tonight - 2008 Remastered",
    "artist": "Frank Sinatra",
    "album": "Nothing But The Best (2008 Remastered)"
  },
  {
    "ts": "2026-07-11T17:41:16.414Z",
    "when": "Jul 11 · 5:41 PM",
    "title": "This Old Dog",
    "artist": "Mac DeMarco",
    "album": "This Old Dog"
  },
  {
    "ts": "2026-07-11T17:38:45.449Z",
    "when": "Jul 11 · 5:38 PM",
    "title": "For the First Time",
    "artist": "Mac DeMarco",
    "album": "This Old Dog"
  },
  {
    "ts": "2026-07-11T17:35:42.680Z",
    "when": "Jul 11 · 5:35 PM",
    "title": "Still Beating",
    "artist": "Mac DeMarco",
    "album": "This Old Dog"
  },
  {
    "ts": "2026-07-11T17:32:40.680Z",
    "when": "Jul 11 · 5:32 PM",
    "title": "One More Love Song",
    "artist": "Mac DeMarco",
    "album": "This Old Dog"
  },
  {
    "ts": "2026-07-11T17:28:39.181Z",
    "when": "Jul 11 · 5:28 PM",
    "title": "On the Level",
    "artist": "Mac DeMarco",
    "album": "This Old Dog"
  },
  {
    "ts": "2026-07-11T16:48:23.809Z",
    "when": "Jul 11 · 4:48 PM",
    "title": "Moonlight on the River",
    "artist": "Mac DeMarco",
    "album": "This Old Dog"
  },
  {
    "ts": "2026-07-11T16:41:20.769Z",
    "when": "Jul 11 · 4:41 PM",
    "title": "Watching Him Fade Away",
    "artist": "Mac DeMarco",
    "album": "This Old Dog"
  },
  {
    "ts": "2026-07-11T16:37:45.417Z",
    "when": "Jul 11 · 4:37 PM",
    "title": "mettle",
    "artist": "she's green",
    "album": "swallowtail"
  },
  {
    "ts": "2026-07-11T03:56:03.225Z",
    "when": "Jul 11 · 3:56 AM",
    "title": "paper thin",
    "artist": "she's green",
    "album": "swallowtail"
  },
  {
    "ts": "2026-07-11T03:52:10.315Z",
    "when": "Jul 11 · 3:52 AM",
    "title": "empty house",
    "artist": "she's green",
    "album": "swallowtail"
  },
  {
    "ts": "2026-07-11T03:48:37.309Z",
    "when": "Jul 11 · 3:48 AM",
    "title": "dear ivy",
    "artist": "she's green",
    "album": "swallowtail"
  },
  {
    "ts": "2026-07-11T03:45:02.421Z",
    "when": "Jul 11 · 3:45 AM",
    "title": "locket",
    "artist": "she's green",
    "album": "swallowtail"
  },
  {
    "ts": "2026-07-11T03:42:02.360Z",
    "when": "Jul 11 · 3:42 AM",
    "title": "Moonlight Sonata 1st Movement",
    "artist": "Ludwig van Beethoven, Marioverehrer",
    "album": "Beethoven's Best Piano Songs"
  },
  {
    "ts": "2026-07-11T02:35:19.092Z",
    "when": "Jul 11 · 2:35 AM",
    "title": "Je te veux",
    "artist": "Erik Satie, Klara Kormendi",
    "album": "Satie (The Best Of)"
  },
  {
    "ts": "2026-07-11T02:30:50.105Z",
    "when": "Jul 11 · 2:30 AM",
    "title": "Mrs. Potter's Garden",
    "artist": "Frerick Den Haan",
    "album": "Mrs. Potter's Garden"
  },
  {
    "ts": "2026-07-11T02:28:11.165Z",
    "when": "Jul 11 · 2:28 AM",
    "title": "Nocturne No. 2 in E-Flat Major, Op. 9 No. 2",
    "artist": "Frédéric Chopin, Daniel Barenboim",
    "album": "Chopin: Nocturnes"
  },
  {
    "ts": "2026-07-11T01:41:12.404Z",
    "when": "Jul 11 · 1:41 AM",
    "title": "Scènes d'enfants: II. Jeux sur la plage, No. 1",
    "artist": "Federico Mompou",
    "album": "Mompou: Complete Piano Works"
  },
  {
    "ts": "2026-07-11T01:39:30.258Z",
    "when": "Jul 11 · 1:39 AM",
    "title": "Gnossienne No. 1",
    "artist": "Erik Satie, Alena Cherny",
    "album": "Gnossienne No. 1"
  },
  {
    "ts": "2026-07-11T01:34:33.213Z",
    "when": "Jul 11 · 1:34 AM",
    "title": "It Breaks (Chapter IX)",
    "artist": "Leon Vynehall",
    "album": "Nothing Is Still"
  },
  {
    "ts": "2026-07-11T01:32:15.593Z",
    "when": "Jul 11 · 1:32 AM",
    "title": "Alicia",
    "artist": "Lorien Testard, Alice Duport-Percier",
    "album": "Clair Obscur: Expedition 33 (Original Soundtrack)"
  },
  {
    "ts": "2026-07-11T01:29:20.665Z",
    "when": "Jul 11 · 1:29 AM",
    "title": "From The Start",
    "artist": "Laufey",
    "album": "Bewitched"
  },
  {
    "ts": "2026-07-11T01:26:30.579Z",
    "when": "Jul 11 · 1:26 AM",
    "title": "Nuvole Bianche",
    "artist": "Ludovico Einaudi",
    "album": "Una Mattina"
  },
  {
    "ts": "2026-07-11T01:20:32.433Z",
    "when": "Jul 11 · 1:20 AM",
    "title": "Forever - Single Version",
    "artist": "The Little Dippers",
    "album": "Forever"
  },
  {
    "ts": "2026-07-11T01:18:08.841Z",
    "when": "Jul 11 · 1:18 AM",
    "title": "Mrs Magic (Strings Version)",
    "artist": "Strawberry Guy",
    "album": "F Song & Mrs Magic (Strings Versions)"
  },
  {
    "ts": "2026-07-11T01:14:26.477Z",
    "when": "Jul 11 · 1:14 AM",
    "title": "By This River - 2004 Digital Remaster",
    "artist": "Brian Eno",
    "album": "Before And After Science"
  },
  {
    "ts": "2026-07-11T01:11:22.585Z",
    "when": "Jul 11 · 1:11 AM",
    "title": "Comptine d'un autre été, l'après-midi",
    "artist": "Yann Tiersen",
    "album": "Le Fabuleux destin d'Amélie Poulain (Bande originale du film)"
  },
  {
    "ts": "2026-07-11T00:28:20.516Z",
    "when": "Jul 11 · 12:28 AM",
    "title": "Gole Maryam",
    "artist": "Giti",
    "album": "Gole Maryam - Persian Music"
  },
  {
    "ts": "2026-07-10T21:49:37.141Z",
    "when": "Jul 10 · 9:49 PM",
    "title": "She Will Destroy You",
    "artist": "Cocteau Twins, Harold Budd",
    "album": "The Moon and the Melodies"
  },
  {
    "ts": "2026-07-10T21:45:18.817Z",
    "when": "Jul 10 · 9:45 PM",
    "title": "Club Social",
    "artist": "Vacations",
    "album": "Changes"
  },
  {
    "ts": "2026-07-10T21:39:51.870Z",
    "when": "Jul 10 · 9:39 PM",
    "title": "Strange Things Will Happen",
    "artist": "The Radio Dept.",
    "album": "Lesser Matters"
  },
  {
    "ts": "2026-07-10T20:59:35.570Z",
    "when": "Jul 10 · 8:59 PM",
    "title": "Natalie Wood",
    "artist": "TV Girl",
    "album": "Natalie Wood"
  },
  {
    "ts": "2026-07-10T20:55:35.007Z",
    "when": "Jul 10 · 8:55 PM",
    "title": "Strawberry Fields Forever - Remastered 2009",
    "artist": "The Beatles",
    "album": "Magical Mystery Tour (Remastered)"
  },
  {
    "ts": "2026-07-10T20:51:27.248Z",
    "when": "Jul 10 · 8:51 PM",
    "title": "Tonight, Tonight - Remastered 2012",
    "artist": "The Smashing Pumpkins",
    "album": "Mellon Collie And The Infinite Sadness (Deluxe Edition)"
  },
  {
    "ts": "2026-07-10T20:42:28.131Z",
    "when": "Jul 10 · 8:42 PM",
    "title": "The Way You'd Love Her",
    "artist": "Mac DeMarco",
    "album": "Another One"
  },
  {
    "ts": "2026-07-10T20:39:51.057Z",
    "when": "Jul 10 · 8:39 PM",
    "title": "At The Wedding",
    "artist": "Tennis",
    "album": "Face Down In The Garden"
  },
  {
    "ts": "2026-07-10T20:30:56.626Z",
    "when": "Jul 10 · 8:30 PM",
    "title": "By Your Side",
    "artist": "Love Spirals Downwards",
    "album": "Flux"
  },
  {
    "ts": "2026-07-10T18:59:38.150Z",
    "when": "Jul 10 · 6:59 PM",
    "title": "Since Yesterday",
    "artist": "Strawberry Switchblade",
    "album": "Strawberry Switchblade"
  },
  {
    "ts": "2026-07-10T18:56:42.232Z",
    "when": "Jul 10 · 6:56 PM",
    "title": "Lucky Love",
    "artist": "Michael Seyer",
    "album": "Bad Bonez"
  },
  {
    "ts": "2026-07-10T18:51:55.598Z",
    "when": "Jul 10 · 6:51 PM",
    "title": "Reminiscing - Remastered 2010",
    "artist": "Little River Band",
    "album": "Sleeper Catcher (Remastered 2022)"
  },
  {
    "ts": "2026-07-10T18:47:37.509Z",
    "when": "Jul 10 · 6:47 PM",
    "title": "Level of Concern",
    "artist": "Twenty One Pilots",
    "album": "Level of Concern"
  },
  {
    "ts": "2026-07-10T18:43:56.807Z",
    "when": "Jul 10 · 6:43 PM",
    "title": "I Want You",
    "artist": "Bob Dylan",
    "album": "Blonde On Blonde"
  },
  {
    "ts": "2026-07-10T18:40:47.748Z",
    "when": "Jul 10 · 6:40 PM",
    "title": "This Guy's In Love With You",
    "artist": "Herb Alpert & The Tijuana Brass",
    "album": "The Beat Of The Brass"
  },
  {
    "ts": "2026-07-10T18:36:47.566Z",
    "when": "Jul 10 · 6:36 PM",
    "title": "Hai Bby",
    "artist": "The Bilinda Butchers",
    "album": "Goodbyes"
  }
]